arrcsv/__init__.py
arrcsv/arrcsv.py
arrcsv-0.0.1.dist-info/LICENSE
arrcsv-0.0.1.dist-info/METADATA
arrcsv-0.0.1.dist-info/WHEEL
arrcsv-0.0.1.dist-info/top_level.txt
arrcsv-0.0.1.dist-info/RECORD
