Metadata-Version: 2.1
Name: arrcsv
Version: 0.0.1
Summary: A python package for converting array to csv
Home-page: https://github.com/saularis/arrcsv
Author: Abdulla Malik
Author-email: hi@abdulla.dev
License: UNKNOWN
Download-URL: https://github.com/saularis/arrcsv/archive/refs/tags/v0.0.1.tar.gz
Project-URL: Bug Tracker, https://github.com/saularis/arrcsv/issues
Keywords: python,convert,array,csv
Platform: UNKNOWN
Classifier: Programming Language :: Python :: 3
Classifier: License :: OSI Approved :: MIT License
Classifier: Operating System :: OS Independent
Requires-Python: >=3.6
Requires-Dist: numpy
